eolchecker/__init__.py
eolchecker/eolchecker.py
eolchecker/models/__init__.py
eolchecker/models/hardwareLifecycle.py
eolchecker/models/softwareLifecycle.py
eolchecker/tools/__init__.py
eolchecker/tools/database.py
eolchecker/tools/downloader.py
eolchecker-0.1.dist-info/LICENSE.md
eolchecker-0.1.dist-info/METADATA
eolchecker-0.1.dist-info/WHEEL
eolchecker-0.1.dist-info/entry_points.txt
eolchecker-0.1.dist-info/top_level.txt
eolchecker-0.1.dist-info/RECORD
