Metadata-Version: 2.1
Name: eolchecker
Version: 0.1
Summary: EOL Checker is a simple application which gathers EOL information for software and hardware and allows you to query locally.
Author-email: Zafer Balkan <zafer@zaferbalkan.com>
License: MIT License
Project-URL: Homepage, https://github.com/zbalkan/eolchecker
Keywords: eol
Classifier: Development Status :: 3 - Alpha
Classifier: Environment :: Console
Classifier: License :: OSI Approved :: MIT License
Classifier: Topic :: System :: Systems Administration
Classifier: Intended Audience :: System Administrators
Classifier: Programming Language :: Python :: 3
Classifier: Programming Language :: Python :: 3.8
Classifier: Programming Language :: Python :: 3.9
Classifier: Programming Language :: Python :: 3.10
Classifier: Programming Language :: Python :: 3.11
Classifier: Programming Language :: Python :: 3 :: Only
Requires-Python: >=3.9
License-File: LICENSE.md
Requires-Dist: argparse >=1.4.0
Requires-Dist: beautifulsoup4 >=4.11.1
Requires-Dist: bs4 >=0.0.1
Requires-Dist: certifi >=2022.6.15
Requires-Dist: charset-normalizer >=2.1.0
Requires-Dist: colorama >=0.4.4
Requires-Dist: idna >=3.3
Requires-Dist: requests >=2.28.1
Requires-Dist: soupsieve >=2.3.2.post1
Requires-Dist: tomli >=2.0.1
Requires-Dist: typing >=3.7.4.3
Requires-Dist: typing-extensions >=4.2.0
Requires-Dist: urllib3 >=1.26.11
Provides-Extra: dev
Requires-Dist: mypy >=0.971 ; extra == 'dev'
Requires-Dist: mypy-extensions >=0.4.3 ; extra == 'dev'
